qdoc2md/__init__.py
qdoc2md/__version__.py
qdoc2md/generator.py
qdoc2md/main.py
qdoc2md/model.py
qdoc2md-0.6.dist-info/METADATA
qdoc2md-0.6.dist-info/WHEEL
qdoc2md-0.6.dist-info/entry_points.txt
qdoc2md-0.6.dist-info/licenses/LICENSE
qdoc2md-0.6.dist-info/RECORD
