Metadata-Version: 2.3
Name: qdoc2md
Version: 0.6
Summary: Convert q documentation comments to Markdown documents
Project-URL: Homepage, https://github.com/darrenwsun/qdoc2md
Project-URL: Issues, https://github.com/darrenwsun/qdoc2md/issues
Author-email: Darren Sun <darren@darrensun.pro>
License-Expression: MIT
License-File: LICENSE
Keywords: kdb,markdown,qdoc
Classifier: Development Status :: 3 - Alpha
Classifier: License :: OSI Approved :: MIT License
Classifier: Programming Language :: Python :: 3
Requires-Python: >=3.8
Requires-Dist: mdutils==1.6
